rdmlpython/LICENSE
rdmlpython/README.md
rdmlpython/__init__.py
rdmlpython/rdml.py
rdmlpython/schema/RDML_v1_0_REC.xsd
rdmlpython/schema/RDML_v1_1_REC.xsd
rdmlpython/schema/RDML_v1_2_REC.xsd
rdmlpython/schema/RDML_v1_3_REC.xsd
rdmlpython-1.7.2.dist-info/LICENSE.txt
rdmlpython-1.7.2.dist-info/METADATA
rdmlpython-1.7.2.dist-info/WHEEL
rdmlpython-1.7.2.dist-info/entry_points.txt
rdmlpython-1.7.2.dist-info/top_level.txt
rdmlpython-1.7.2.dist-info/RECORD
