Metadata-Version: 2.1
Name: rdmlpython
Version: 1.7.2
Summary: A package to read and edit RDML files.
Home-page: https://github.com/RDML-consortium/rdmlpython
Author: Andreas Untergasser
Author-email: andreas@untergasser.de
License: MIT
Platform: UNKNOWN
License-File: LICENSE.txt
Requires-Dist: lxml (>=4.2.1)
Requires-Dist: matplotlib (>=3.5.1)
Requires-Dist: numpy (>=1.17.2)
Requires-Dist: scipy (>=1.3.1)
